statistics/__init__.py
statistics-3.4.0b3.dist-info/DESCRIPTION.rst
statistics-3.4.0b3.dist-info/METADATA
statistics-3.4.0b3.dist-info/RECORD
statistics-3.4.0b3.dist-info/WHEEL
statistics-3.4.0b3.dist-info/metadata.json
statistics-3.4.0b3.dist-info/top_level.txt
