Metadata-Version: 1.1
Name: statistics
Version: 3.4.0b3
Summary: A Python 2.* port of 3.4 Statistics Module
Home-page: https://github.com/digitalemagine/py-statistics
Author: Stefano Crosta
Author-email: stefano@digitalemagine.com
License: PSF License
Keywords: statistics
Platform: UNKNOWN
Classifier: Development Status :: 5 - Production/Stable
Classifier: Intended Audience :: Developers
Classifier: License :: OSI Approved :: Python Software Foundation License
Classifier: Programming Language :: Python :: 2
Classifier: Programming Language :: Python :: 2.6
Classifier: Programming Language :: Python :: 2.7
